zuspec/be/sv/__init__.py
zuspec/be/sv/__version__.py
zuspec/be/sv/_version.py
zuspec/be/sv/generator.py
zuspec_be_sv-0.0.1.21346837069rc0.dist-info/licenses/LICENSE
zuspec_be_sv-0.0.1.21346837069rc0.dist-info/METADATA
zuspec_be_sv-0.0.1.21346837069rc0.dist-info/WHEEL
zuspec_be_sv-0.0.1.21346837069rc0.dist-info/top_level.txt
zuspec_be_sv-0.0.1.21346837069rc0.dist-info/RECORD
