Metadata-Version: 2.4
Name: zuspec-be-sv
Version: 0.0.1.21346837069rc0
Summary: Zuspec SystemVerilog backend
Author-email: Matthew Ballance <matt.ballance@gmail.com>
License: Apache-2.0
Project-URL: Homepage, https://github.com/zuspec/zuspec-be-sv-simplify
Project-URL: Repository, https://github.com/zuspec/zuspec-be-sv-simplify
Requires-Python: >=3.7
License-File: LICENSE
Provides-Extra: dev
Requires-Dist: pytest>=6.0; extra == "dev"
Requires-Dist: pytest-dfm; extra == "dev"
Requires-Dist: zuspec-dataclasses; extra == "dev"
Requires-Dist: zuspec-be-sw; extra == "dev"
Requires-Dist: pyhdl-if; extra == "dev"
Requires-Dist: gemini-riscv; extra == "dev"
Requires-Dist: Sphinx; extra == "dev"
Requires-Dist: sphinx-argparse; extra == "dev"
Requires-Dist: sphinxcontrib-makedomain; extra == "dev"
Requires-Dist: sphinxcontrib-spelling; extra == "dev"
Requires-Dist: sphinx-rtd-theme; extra == "dev"
Dynamic: license-file
